via_varejo/__init__.py
via_varejo/via.py
via_varejo-0.1.1.dist-info/WHEEL
via_varejo-0.1.1.dist-info/METADATA
via_varejo-0.1.1.dist-info/RECORD
